emotionpyy/__init__.py
emotionpyy-0.0.1.dist-info/METADATA
emotionpyy-0.0.1.dist-info/RECORD
emotionpyy-0.0.1.dist-info/WHEEL
emotionpyy-0.0.1.dist-info/top_level.txt
