Metadata-Version: 2.1
Name: emotionpyy
Version: 0.0.1
Summary: Detecting emotions behind the text, pyemotionpyy package will help you to understand the emotions in textual meassages.
Home-page: https://github.com/aman2656/pyemotion_library
Author: Pyemotion Team
Author-email: pyemotionteam@gmail.com
License: MIT
Platform: UNKNOWN
Classifier: License :: OSI Approved :: MIT License
Classifier: Programming Language :: Python :: 3
Requires-Python: >=3.6
Requires-Dist: nltk (>=3.5)
Requires-Dist: numpy (>=1.19.1)
Requires-Dist: emoji (>=0.6.0)
Requires-Dist: pandas (>=1.1.0)
